tcbench/FIGSHARE_RESOURCES.yml
tcbench/__init__.py
tcbench/cli/__init__.py
tcbench/cli/clickutils.py
tcbench/cli/command_aimrepo.py
tcbench/cli/command_campaign.py
tcbench/cli/command_datasets.py
tcbench/cli/command_fetchartifacts.py
tcbench/cli/command_singlerun.py
tcbench/cli/main.py
tcbench/cli/rich.theme
tcbench/cli/richutils.py
tcbench/libtcdatasets/__init__.py
tcbench/libtcdatasets/datasets_utils.py
tcbench/libtcdatasets/mirage19_generate_splits.py
tcbench/libtcdatasets/mirage19_json_to_parquet.py
tcbench/libtcdatasets/mirage22_generate_splits.py
tcbench/libtcdatasets/mirage22_json_to_parquet.py
tcbench/libtcdatasets/ucdavis_icdm19_csv_to_parquet.py
tcbench/libtcdatasets/ucdavis_icdm19_generate_splits.py
tcbench/libtcdatasets/utmobilenet21_csv_to_parquet.py
tcbench/libtcdatasets/utmobilenet21_generate_splits.py
tcbench/libtcdatasets/resources/DATASETS.yml
tcbench/libtcdatasets/resources/DATASETS_FILES_MD5.yml
tcbench/libtcdatasets/resources/mirage19.yml
tcbench/libtcdatasets/resources/mirage22.yml
tcbench/libtcdatasets/resources/ucdavis-icdm19.yml
tcbench/libtcdatasets/resources/utmobilenet21.yml
tcbench/modeling/__init__.py
tcbench/modeling/aimutils.py
tcbench/modeling/augmentation.py
tcbench/modeling/backbone.py
tcbench/modeling/dataprep.py
tcbench/modeling/losses.py
tcbench/modeling/methods.py
tcbench/modeling/run_augmentations_at_loading.py
tcbench/modeling/run_augmentations_at_loading_xgboost.py
tcbench/modeling/run_campaign_augmentations_at_loading.py
tcbench/modeling/run_campaign_augmentations_at_loading_xgboost.py
tcbench/modeling/run_campaign_contrastive_learning_and_finetune.py
tcbench/modeling/run_contrastive_learning_and_finetune.py
tcbench/modeling/utils.py
tcbench/scripts/generate_datasets_schemas.py
tcbench-0.0.22.dist-info/LICENSE
tcbench-0.0.22.dist-info/METADATA
tcbench-0.0.22.dist-info/WHEEL
tcbench-0.0.22.dist-info/entry_points.txt
tcbench-0.0.22.dist-info/top_level.txt
tcbench-0.0.22.dist-info/RECORD
