Metadata-Version: 2.1
Name: tcbench
Version: 0.0.22
Summary: A ML/DL framework for Traffic Classification
Author-email: Alessandro Finamore <alessandro.finamore@huawei.com>
License: MIT License
Project-URL: Homepage, https://tcbenchstack.github.io/tcbench/
Keywords: machine learning,deep learning,traffic classification,time series
Classifier: License :: OSI Approved :: MIT License
Classifier: Programming Language :: Python
Classifier: Programming Language :: Python :: 3
Requires-Python: >=3.9
License-File: LICENSE
Requires-Dist: aim ==3.17.4
Requires-Dist: autorank
Requires-Dist: click
Requires-Dist: dask <=2023.5.1
Requires-Dist: distributed
Requires-Dist: numpy
Requires-Dist: pandas ==2.0.2
Requires-Dist: pyarrow ==12.0.0
Requires-Dist: pyyaml
Requires-Dist: requests
Requires-Dist: rich
Requires-Dist: rich-click
Requires-Dist: scikit-learn
Requires-Dist: statsmodels
Requires-Dist: torch ==2.0.1
Requires-Dist: torchsummary
Requires-Dist: torchvision ==0.15.2
Requires-Dist: xgboost ==1.7.5
Provides-Extra: dev
Requires-Dist: black ; extra == 'dev'
Requires-Dist: bumpver ; extra == 'dev'
Requires-Dist: click-plugins ; extra == 'dev'
Requires-Dist: isort ; extra == 'dev'
Requires-Dist: jupyterlab ; extra == 'dev'
Requires-Dist: matplotlib ; extra == 'dev'
Requires-Dist: mkdocs ; extra == 'dev'
Requires-Dist: mkdocs-autorefs ; extra == 'dev'
Requires-Dist: mkdocs-glightbox ; extra == 'dev'
Requires-Dist: mkdocs-jupyter ; extra == 'dev'
Requires-Dist: mkdocs-material ; extra == 'dev'
Requires-Dist: mkdocs-material-extensions ; extra == 'dev'
Requires-Dist: mkdocs-table-reader-plugin ; extra == 'dev'
Requires-Dist: mkdocstrings ; extra == 'dev'
Requires-Dist: mkdocstrings-python ; extra == 'dev'
Requires-Dist: pip-tools ; extra == 'dev'
Requires-Dist: pytest ; extra == 'dev'
Requires-Dist: pytest-helpers-namespace ; extra == 'dev'
Requires-Dist: seaborn ; extra == 'dev'
